dagdeployer/__init__.py
dagdeployer/deploy_dag.py
deployer/__init__.py
deployer/deploy_dag.py
airflow_dag_deployer-0.5.dist-info/METADATA
airflow_dag_deployer-0.5.dist-info/WHEEL
airflow_dag_deployer-0.5.dist-info/entry_points.txt
airflow_dag_deployer-0.5.dist-info/top_level.txt
airflow_dag_deployer-0.5.dist-info/RECORD
